omnipy_example_data/__init__.py
omnipy_example_data/bif/LICENSE
omnipy_example_data/bif/asia.bif
omnipy_example_data/gff/GCF_000002945.1_ASM294v2_genomic.gff
omnipy_example_data/gff/GCF_000146045.2_R64_genomic.gff
omnipy_example_data/gff/LICENSE
omnipy_example_data/isa-json/LICENSE
omnipy_example_data/isa-json/isa_seek-investigation19.json
omnipy_example_data/isa-json/isa_seek-investigation20_p14.json
omnipy_example_data/isa-json/isa_seek-investigation21_p14.json
omnipy_example_data-0.1.0.dist-info/WHEEL
omnipy_example_data-0.1.0.dist-info/METADATA
omnipy_example_data-0.1.0.dist-info/RECORD
